gns3_net_converter-1.3.0.dist-info/DESCRIPTION.rst
gns3_net_converter-1.3.0.dist-info/METADATA
gns3_net_converter-1.3.0.dist-info/RECORD
gns3_net_converter-1.3.0.dist-info/WHEEL
gns3_net_converter-1.3.0.dist-info/entry_points.txt
gns3_net_converter-1.3.0.dist-info/metadata.json
gns3_net_converter-1.3.0.dist-info/top_level.txt
gns3converter/__init__.py
gns3converter/adapters.py
gns3converter/configspec
gns3converter/converter.py
gns3converter/converterror.py
gns3converter/interfaces.py
gns3converter/main.py
gns3converter/models.py
gns3converter/node.py
gns3converter/topology.py
gns3converter/utils.py
