Metadata-Version: 2.0
Name: gns3-net-converter
Version: 1.3.0
Summary: Official fork by GNS3 team of the gns3 converter.Convert old ini-style GNS3 topologies (<=0.8.7) to the newer version 1+ JSON format
Home-page: https://github.com/gns3/gns3-converter
Author: GNS3 Team
Author-email: developers@gns3.net
License: GPLv3+
Platform: any
Classifier: Development Status :: 5 - Production/Stable
Classifier: Environment :: Console
Classifier: Intended Audience :: Education
Classifier: Intended Audience :: Information Technology
Classifier: License :: OSI Approved :: GNU General Public License v3 or later (GPLv3+)
Classifier: Natural Language :: English
Classifier: Operating System :: OS Independent
Classifier: Programming Language :: Python :: 3
Classifier: Programming Language :: Python :: 3.3
Classifier: Programming Language :: Python :: 3.4
Classifier: Topic :: Education
Classifier: Topic :: Utilities
Requires-Dist: configobj
